README.md
setup.py
apv_databases.egg-info/PKG-INFO
apv_databases.egg-info/SOURCES.txt
apv_databases.egg-info/dependency_links.txt
apv_databases.egg-info/top_level.txt
mypylib/__init__.py
mypylib/mongo.py