Metadata-Version: 1.0
Name: apv-databases
Version: 0.1.0
Summary: My first Python library
Home-page: UNKNOWN
Author: Me
Author-email: UNKNOWN
License: MIT
Platform: UNKNOWN
